fastpynuts/__init__.py
fastpynuts/download.py
fastpynuts/experimental.py
fastpynuts/fastpynuts.py
fastpynuts/utils.py
fastpynuts-1.3.0.dist-info/LICENSE
fastpynuts-1.3.0.dist-info/METADATA
fastpynuts-1.3.0.dist-info/WHEEL
fastpynuts-1.3.0.dist-info/top_level.txt
fastpynuts-1.3.0.dist-info/RECORD
