Metadata-Version: 2.1
Name: fastpynuts
Version: 1.3.0
Summary: A fast implementation of querying for NUTS regions by location.
Author-email: Colin Moldenhauer <colin.moldenhauer@tum.de>, Michael Engel <m.engel@tum.de>
Project-URL: Homepage, https://github.com/ColinMoldenhauer/FastPyNUTS
Project-URL: Issues, https://github.com/ColinMoldenhauer/FastPyNUTS/issues
Keywords: eurostat,NUTS,nomenclature of territorial units for statistics
Classifier: Programming Language :: Python :: 3
Classifier: License :: OSI Approved :: GNU General Public License v3 (GPLv3)
Classifier: Operating System :: OS Independent
Requires-Python: >=3.8
License-File: LICENSE
Requires-Dist: shapely >=2.0
Requires-Dist: numpy
Requires-Dist: rtree
Requires-Dist: treelib
